neuron_explainer/__init__.py
neuron_explainer/activations/__init__.py
neuron_explainer/activations/activation_records.py
neuron_explainer/activations/activations.py
neuron_explainer/activations/attention_utils.py
neuron_explainer/activations/token_connections.py
neuron_explainer/api_client.py
neuron_explainer/azure.py
neuron_explainer/explanations/__init__.py
neuron_explainer/explanations/calibrated_simulator.py
neuron_explainer/explanations/explainer.py
neuron_explainer/explanations/explanations.py
neuron_explainer/explanations/few_shot_examples.py
neuron_explainer/explanations/prompt_builder.py
neuron_explainer/explanations/puzzles.json
neuron_explainer/explanations/puzzles.py
neuron_explainer/explanations/scoring.py
neuron_explainer/explanations/simulator.py
neuron_explainer/explanations/test_explainer.py
neuron_explainer/explanations/test_simulator.py
neuron_explainer/explanations/token_space_few_shot_examples.py
neuron_explainer/fast_dataclasses/__init__.py
neuron_explainer/fast_dataclasses/fast_dataclasses.py
neuron_explainer/fast_dataclasses/test_fast_dataclasses.py
automated_interpretability-0.0.18.dist-info/METADATA
automated_interpretability-0.0.18.dist-info/WHEEL
automated_interpretability-0.0.18.dist-info/licenses/LICENSE
automated_interpretability-0.0.18.dist-info/RECORD
